COPYING.md
MANIFEST.in
README.md
setup.cfg
setup.py
rlieh_pwm/__init__.py
rlieh_pwm/cli.py
rlieh_pwm/cli_ada.py
rlieh_pwm/core.py
rlieh_pwm/tests.py
rlieh_pwm.egg-info/PKG-INFO
rlieh_pwm.egg-info/SOURCES.txt
rlieh_pwm.egg-info/dependency_links.txt
rlieh_pwm.egg-info/entry_points.txt
rlieh_pwm.egg-info/requires.txt
rlieh_pwm.egg-info/top_level.txt