Metadata-Version: 1.1
Name: rlieh-pwm
Version: 0.0.7
Summary: This module provides an interface to manage PWM on RLIEH systems
Home-page: http://github.com/owatte/rlieh-pwm
Author: Olivier Watté - RLIEH project
Author-email: owatte@lebiklab.com
License: UNKNOWN
Platform: UNKNOWN
Classifier: Programming Language :: Python
Classifier: Development Status :: 3 - Alpha
Classifier: Environment :: Console
Classifier: License :: OSI Approved :: GNU General Public License v3 or later (GPLv3+)
Classifier: Intended Audience :: Science/Research
Classifier: Natural Language :: English
Classifier: Operating System :: OS Independent
Classifier: Programming Language :: Python :: 3
Classifier: Topic :: Scientific/Engineering
